<annotation>
	<folder></folder>
	<filename>00074_jpg.rf.af6087467800598f4edef879fbbf24e4.jpg</filename>
	<path>00074_jpg.rf.af6087467800598f4edef879fbbf24e4.jpg</path>
	<source>
		<database>roboflow.ai</database>
	</source>
	<size>
		<width>300</width>
		<height>300</height>
		<depth>3</depth>
	</size>
	<segmented>0</segmented>
	<object>
		<name>red</name>
		<pose>Unspecified</pose>
		<truncated>0</truncated>
		<difficult>0</difficult>
		<occluded>0</occluded>
		<bndbox>
			<xmin>176</xmin>
			<xmax>212</xmax>
			<ymin>27</ymin>
			<ymax>97</ymax>
		</bndbox>
	</object>
	<object>
		<name>yellow</name>
		<pose>Unspecified</pose>
		<truncated>0</truncated>
		<difficult>0</difficult>
		<occluded>0</occluded>
		<bndbox>
			<xmin>62</xmin>
			<xmax>98</xmax>
			<ymin>28</ymin>
			<ymax>97</ymax>
		</bndbox>
	</object>
</annotation>
