<annotation>
	<folder></folder>
	<filename>00724_jpg.rf.856ea6290cbbaf05daa5416c505d7d22.jpg</filename>
	<path>00724_jpg.rf.856ea6290cbbaf05daa5416c505d7d22.jpg</path>
	<source>
		<database>roboflow.ai</database>
	</source>
	<size>
		<width>300</width>
		<height>300</height>
		<depth>3</depth>
	</size>
	<segmented>0</segmented>
	<object>
		<name>none</name>
		<pose>Unspecified</pose>
		<truncated>0</truncated>
		<difficult>0</difficult>
		<occluded>0</occluded>
		<bndbox>
			<xmin>176</xmin>
			<xmax>196</xmax>
			<ymin>140</ymin>
			<ymax>189</ymax>
		</bndbox>
	</object>
	<object>
		<name>none</name>
		<pose>Unspecified</pose>
		<truncated>0</truncated>
		<difficult>0</difficult>
		<occluded>0</occluded>
		<bndbox>
			<xmin>222</xmin>
			<xmax>240</xmax>
			<ymin>132</ymin>
			<ymax>178</ymax>
		</bndbox>
	</object>
	<object>
		<name>none</name>
		<pose>Unspecified</pose>
		<truncated>0</truncated>
		<difficult>0</difficult>
		<occluded>0</occluded>
		<bndbox>
			<xmin>164</xmin>
			<xmax>172</xmax>
			<ymin>153</ymin>
			<ymax>172</ymax>
		</bndbox>
	</object>
	<object>
		<name>none</name>
		<pose>Unspecified</pose>
		<truncated>0</truncated>
		<difficult>0</difficult>
		<occluded>0</occluded>
		<bndbox>
			<xmin>120</xmin>
			<xmax>129</xmax>
			<ymin>148</ymin>
			<ymax>167</ymax>
		</bndbox>
	</object>
	<object>
		<name>red</name>
		<pose>Unspecified</pose>
		<truncated>0</truncated>
		<difficult>0</difficult>
		<occluded>0</occluded>
		<bndbox>
			<xmin>142</xmin>
			<xmax>151</xmax>
			<ymin>153</ymin>
			<ymax>174</ymax>
		</bndbox>
	</object>
	<object>
		<name>white</name>
		<pose>Unspecified</pose>
		<truncated>0</truncated>
		<difficult>0</difficult>
		<occluded>0</occluded>
		<bndbox>
			<xmin>265</xmin>
			<xmax>284</xmax>
			<ymin>148</ymin>
			<ymax>197</ymax>
		</bndbox>
	</object>
</annotation>
