<annotation>
	<folder></folder>
	<filename>01361_jpg.rf.6d4e56ccbad629bf1d86f409e67a918d.jpg</filename>
	<path>01361_jpg.rf.6d4e56ccbad629bf1d86f409e67a918d.jpg</path>
	<source>
		<database>roboflow.ai</database>
	</source>
	<size>
		<width>300</width>
		<height>300</height>
		<depth>3</depth>
	</size>
	<segmented>0</segmented>
	<object>
		<name>none</name>
		<pose>Unspecified</pose>
		<truncated>0</truncated>
		<difficult>0</difficult>
		<occluded>0</occluded>
		<bndbox>
			<xmin>17</xmin>
			<xmax>25</xmax>
			<ymin>90</ymin>
			<ymax>107</ymax>
		</bndbox>
	</object>
	<object>
		<name>none</name>
		<pose>Unspecified</pose>
		<truncated>0</truncated>
		<difficult>0</difficult>
		<occluded>0</occluded>
		<bndbox>
			<xmin>49</xmin>
			<xmax>61</xmax>
			<ymin>93</ymin>
			<ymax>115</ymax>
		</bndbox>
	</object>
	<object>
		<name>none</name>
		<pose>Unspecified</pose>
		<truncated>0</truncated>
		<difficult>0</difficult>
		<occluded>0</occluded>
		<bndbox>
			<xmin>117</xmin>
			<xmax>125</xmax>
			<ymin>98</ymin>
			<ymax>114</ymax>
		</bndbox>
	</object>
	<object>
		<name>none</name>
		<pose>Unspecified</pose>
		<truncated>0</truncated>
		<difficult>0</difficult>
		<occluded>0</occluded>
		<bndbox>
			<xmin>122</xmin>
			<xmax>132</xmax>
			<ymin>89</ymin>
			<ymax>109</ymax>
		</bndbox>
	</object>
	<object>
		<name>none</name>
		<pose>Unspecified</pose>
		<truncated>0</truncated>
		<difficult>0</difficult>
		<occluded>0</occluded>
		<bndbox>
			<xmin>167</xmin>
			<xmax>177</xmax>
			<ymin>97</ymin>
			<ymax>117</ymax>
		</bndbox>
	</object>
	<object>
		<name>none</name>
		<pose>Unspecified</pose>
		<truncated>0</truncated>
		<difficult>0</difficult>
		<occluded>0</occluded>
		<bndbox>
			<xmin>203</xmin>
			<xmax>213</xmax>
			<ymin>102</ymin>
			<ymax>122</ymax>
		</bndbox>
	</object>
	<object>
		<name>none</name>
		<pose>Unspecified</pose>
		<truncated>0</truncated>
		<difficult>0</difficult>
		<occluded>0</occluded>
		<bndbox>
			<xmin>212</xmin>
			<xmax>218</xmax>
			<ymin>109</ymin>
			<ymax>119</ymax>
		</bndbox>
	</object>
	<object>
		<name>none</name>
		<pose>Unspecified</pose>
		<truncated>0</truncated>
		<difficult>0</difficult>
		<occluded>0</occluded>
		<bndbox>
			<xmin>225</xmin>
			<xmax>233</xmax>
			<ymin>111</ymin>
			<ymax>125</ymax>
		</bndbox>
	</object>
	<object>
		<name>none</name>
		<pose>Unspecified</pose>
		<truncated>0</truncated>
		<difficult>0</difficult>
		<occluded>0</occluded>
		<bndbox>
			<xmin>261</xmin>
			<xmax>272</xmax>
			<ymin>104</ymin>
			<ymax>123</ymax>
		</bndbox>
	</object>
	<object>
		<name>none</name>
		<pose>Unspecified</pose>
		<truncated>0</truncated>
		<difficult>0</difficult>
		<occluded>0</occluded>
		<bndbox>
			<xmin>272</xmin>
			<xmax>282</xmax>
			<ymin>113</ymin>
			<ymax>129</ymax>
		</bndbox>
	</object>
	<object>
		<name>white</name>
		<pose>Unspecified</pose>
		<truncated>0</truncated>
		<difficult>0</difficult>
		<occluded>0</occluded>
		<bndbox>
			<xmin>255</xmin>
			<xmax>260</xmax>
			<ymin>117</ymin>
			<ymax>127</ymax>
		</bndbox>
	</object>
	<object>
		<name>red</name>
		<pose>Unspecified</pose>
		<truncated>0</truncated>
		<difficult>0</difficult>
		<occluded>0</occluded>
		<bndbox>
			<xmin>88</xmin>
			<xmax>100</xmax>
			<ymin>86</ymin>
			<ymax>108</ymax>
		</bndbox>
	</object>
	<object>
		<name>red</name>
		<pose>Unspecified</pose>
		<truncated>0</truncated>
		<difficult>0</difficult>
		<occluded>0</occluded>
		<bndbox>
			<xmin>137</xmin>
			<xmax>145</xmax>
			<ymin>99</ymin>
			<ymax>114</ymax>
		</bndbox>
	</object>
	<object>
		<name>red</name>
		<pose>Unspecified</pose>
		<truncated>0</truncated>
		<difficult>0</difficult>
		<occluded>0</occluded>
		<bndbox>
			<xmin>163</xmin>
			<xmax>169</xmax>
			<ymin>103</ymin>
			<ymax>118</ymax>
		</bndbox>
	</object>
</annotation>
