<annotation>
	<folder></folder>
	<filename>01897_jpg.rf.eef9e2c805ccb7e4ddf5faef515604df.jpg</filename>
	<path>01897_jpg.rf.eef9e2c805ccb7e4ddf5faef515604df.jpg</path>
	<source>
		<database>roboflow.ai</database>
	</source>
	<size>
		<width>300</width>
		<height>300</height>
		<depth>3</depth>
	</size>
	<segmented>0</segmented>
	<object>
		<name>yellow</name>
		<pose>Unspecified</pose>
		<truncated>0</truncated>
		<difficult>0</difficult>
		<occluded>0</occluded>
		<bndbox>
			<xmin>136</xmin>
			<xmax>162</xmax>
			<ymin>23</ymin>
			<ymax>79</ymax>
		</bndbox>
	</object>
	<object>
		<name>yellow</name>
		<pose>Unspecified</pose>
		<truncated>0</truncated>
		<difficult>0</difficult>
		<occluded>0</occluded>
		<bndbox>
			<xmin>210</xmin>
			<xmax>226</xmax>
			<ymin>72</ymin>
			<ymax>104</ymax>
		</bndbox>
	</object>
	<object>
		<name>yellow</name>
		<pose>Unspecified</pose>
		<truncated>0</truncated>
		<difficult>0</difficult>
		<occluded>0</occluded>
		<bndbox>
			<xmin>269</xmin>
			<xmax>293</xmax>
			<ymin>45</ymin>
			<ymax>85</ymax>
		</bndbox>
	</object>
	<object>
		<name>yellow</name>
		<pose>Unspecified</pose>
		<truncated>0</truncated>
		<difficult>0</difficult>
		<occluded>0</occluded>
		<bndbox>
			<xmin>11</xmin>
			<xmax>32</xmax>
			<ymin>73</ymin>
			<ymax>107</ymax>
		</bndbox>
	</object>
</annotation>
