<annotation>
	<folder></folder>
	<filename>01917_jpg.rf.0cb702ae15cd20738ef69cb008daf3bd.jpg</filename>
	<path>01917_jpg.rf.0cb702ae15cd20738ef69cb008daf3bd.jpg</path>
	<source>
		<database>roboflow.ai</database>
	</source>
	<size>
		<width>300</width>
		<height>300</height>
		<depth>3</depth>
	</size>
	<segmented>0</segmented>
	<object>
		<name>yellow</name>
		<pose>Unspecified</pose>
		<truncated>0</truncated>
		<difficult>0</difficult>
		<occluded>0</occluded>
		<bndbox>
			<xmin>95</xmin>
			<xmax>109</xmax>
			<ymin>77</ymin>
			<ymax>89</ymax>
		</bndbox>
	</object>
	<object>
		<name>white</name>
		<pose>Unspecified</pose>
		<truncated>0</truncated>
		<difficult>0</difficult>
		<occluded>0</occluded>
		<bndbox>
			<xmin>62</xmin>
			<xmax>78</xmax>
			<ymin>204</ymin>
			<ymax>214</ymax>
		</bndbox>
	</object>
</annotation>
