<annotation>
	<folder></folder>
	<filename>02104_jpg.rf.7c7f9f2bbf4113a519cdd0b4cfe60fbd.jpg</filename>
	<path>02104_jpg.rf.7c7f9f2bbf4113a519cdd0b4cfe60fbd.jpg</path>
	<source>
		<database>roboflow.ai</database>
	</source>
	<size>
		<width>300</width>
		<height>300</height>
		<depth>3</depth>
	</size>
	<segmented>0</segmented>
	<object>
		<name>yellow</name>
		<pose>Unspecified</pose>
		<truncated>0</truncated>
		<difficult>0</difficult>
		<occluded>0</occluded>
		<bndbox>
			<xmin>177</xmin>
			<xmax>192</xmax>
			<ymin>76</ymin>
			<ymax>107</ymax>
		</bndbox>
	</object>
	<object>
		<name>yellow</name>
		<pose>Unspecified</pose>
		<truncated>0</truncated>
		<difficult>0</difficult>
		<occluded>0</occluded>
		<bndbox>
			<xmin>195</xmin>
			<xmax>210</xmax>
			<ymin>69</ymin>
			<ymax>98</ymax>
		</bndbox>
	</object>
	<object>
		<name>yellow</name>
		<pose>Unspecified</pose>
		<truncated>0</truncated>
		<difficult>0</difficult>
		<occluded>0</occluded>
		<bndbox>
			<xmin>220</xmin>
			<xmax>232</xmax>
			<ymin>65</ymin>
			<ymax>89</ymax>
		</bndbox>
	</object>
	<object>
		<name>yellow</name>
		<pose>Unspecified</pose>
		<truncated>0</truncated>
		<difficult>0</difficult>
		<occluded>0</occluded>
		<bndbox>
			<xmin>192</xmin>
			<xmax>197</xmax>
			<ymin>75</ymin>
			<ymax>99</ymax>
		</bndbox>
	</object>
	<object>
		<name>blue</name>
		<pose>Unspecified</pose>
		<truncated>0</truncated>
		<difficult>0</difficult>
		<occluded>0</occluded>
		<bndbox>
			<xmin>164</xmin>
			<xmax>178</xmax>
			<ymin>61</ymin>
			<ymax>91</ymax>
		</bndbox>
	</object>
	<object>
		<name>blue</name>
		<pose>Unspecified</pose>
		<truncated>0</truncated>
		<difficult>0</difficult>
		<occluded>0</occluded>
		<bndbox>
			<xmin>152</xmin>
			<xmax>166</xmax>
			<ymin>58</ymin>
			<ymax>91</ymax>
		</bndbox>
	</object>
	<object>
		<name>red</name>
		<pose>Unspecified</pose>
		<truncated>0</truncated>
		<difficult>0</difficult>
		<occluded>0</occluded>
		<bndbox>
			<xmin>148</xmin>
			<xmax>161</xmax>
			<ymin>53</ymin>
			<ymax>77</ymax>
		</bndbox>
	</object>
	<object>
		<name>red</name>
		<pose>Unspecified</pose>
		<truncated>0</truncated>
		<difficult>0</difficult>
		<occluded>0</occluded>
		<bndbox>
			<xmin>135</xmin>
			<xmax>149</xmax>
			<ymin>59</ymin>
			<ymax>84</ymax>
		</bndbox>
	</object>
	<object>
		<name>white</name>
		<pose>Unspecified</pose>
		<truncated>0</truncated>
		<difficult>0</difficult>
		<occluded>0</occluded>
		<bndbox>
			<xmin>208</xmin>
			<xmax>223</xmax>
			<ymin>56</ymin>
			<ymax>88</ymax>
		</bndbox>
	</object>
	<object>
		<name>blue</name>
		<pose>Unspecified</pose>
		<truncated>0</truncated>
		<difficult>0</difficult>
		<occluded>0</occluded>
		<bndbox>
			<xmin>231</xmin>
			<xmax>247</xmax>
			<ymin>65</ymin>
			<ymax>98</ymax>
		</bndbox>
	</object>
	<object>
		<name>yellow</name>
		<pose>Unspecified</pose>
		<truncated>0</truncated>
		<difficult>0</difficult>
		<occluded>0</occluded>
		<bndbox>
			<xmin>243</xmin>
			<xmax>258</xmax>
			<ymin>61</ymin>
			<ymax>90</ymax>
		</bndbox>
	</object>
	<object>
		<name>yellow</name>
		<pose>Unspecified</pose>
		<truncated>0</truncated>
		<difficult>0</difficult>
		<occluded>0</occluded>
		<bndbox>
			<xmin>262</xmin>
			<xmax>280</xmax>
			<ymin>62</ymin>
			<ymax>97</ymax>
		</bndbox>
	</object>
</annotation>
