<annotation>
	<folder></folder>
	<filename>02620_jpg.rf.30aabffb6a700199228595c7dbaae44c.jpg</filename>
	<path>02620_jpg.rf.30aabffb6a700199228595c7dbaae44c.jpg</path>
	<source>
		<database>roboflow.ai</database>
	</source>
	<size>
		<width>300</width>
		<height>300</height>
		<depth>3</depth>
	</size>
	<segmented>0</segmented>
	<object>
		<name>white</name>
		<pose>Unspecified</pose>
		<truncated>0</truncated>
		<difficult>0</difficult>
		<occluded>0</occluded>
		<bndbox>
			<xmin>188</xmin>
			<xmax>217</xmax>
			<ymin>81</ymin>
			<ymax>138</ymax>
		</bndbox>
	</object>
</annotation>
