<annotation>
	<folder></folder>
	<filename>03259_jpg.rf.860476f1a61042252db1d74d533c9deb.jpg</filename>
	<path>03259_jpg.rf.860476f1a61042252db1d74d533c9deb.jpg</path>
	<source>
		<database>roboflow.ai</database>
	</source>
	<size>
		<width>300</width>
		<height>300</height>
		<depth>3</depth>
	</size>
	<segmented>0</segmented>
	<object>
		<name>yellow</name>
		<pose>Unspecified</pose>
		<truncated>0</truncated>
		<difficult>0</difficult>
		<occluded>0</occluded>
		<bndbox>
			<xmin>190</xmin>
			<xmax>200</xmax>
			<ymin>226</ymin>
			<ymax>243</ymax>
		</bndbox>
	</object>
	<object>
		<name>yellow</name>
		<pose>Unspecified</pose>
		<truncated>0</truncated>
		<difficult>0</difficult>
		<occluded>0</occluded>
		<bndbox>
			<xmin>232</xmin>
			<xmax>240</xmax>
			<ymin>55</ymin>
			<ymax>68</ymax>
		</bndbox>
	</object>
	<object>
		<name>red</name>
		<pose>Unspecified</pose>
		<truncated>0</truncated>
		<difficult>0</difficult>
		<occluded>0</occluded>
		<bndbox>
			<xmin>197</xmin>
			<xmax>205</xmax>
			<ymin>112</ymin>
			<ymax>125</ymax>
		</bndbox>
	</object>
	<object>
		<name>white</name>
		<pose>Unspecified</pose>
		<truncated>0</truncated>
		<difficult>0</difficult>
		<occluded>0</occluded>
		<bndbox>
			<xmin>263</xmin>
			<xmax>270</xmax>
			<ymin>108</ymin>
			<ymax>120</ymax>
		</bndbox>
	</object>
	<object>
		<name>red</name>
		<pose>Unspecified</pose>
		<truncated>0</truncated>
		<difficult>0</difficult>
		<occluded>0</occluded>
		<bndbox>
			<xmin>219</xmin>
			<xmax>229</xmax>
			<ymin>246</ymin>
			<ymax>262</ymax>
		</bndbox>
	</object>
</annotation>
