<annotation>
	<folder></folder>
	<filename>03363_jpg.rf.6290bdf6d031ed556f44a92d5b150514.jpg</filename>
	<path>03363_jpg.rf.6290bdf6d031ed556f44a92d5b150514.jpg</path>
	<source>
		<database>roboflow.ai</database>
	</source>
	<size>
		<width>300</width>
		<height>300</height>
		<depth>3</depth>
	</size>
	<segmented>0</segmented>
	<object>
		<name>yellow</name>
		<pose>Unspecified</pose>
		<truncated>0</truncated>
		<difficult>0</difficult>
		<occluded>0</occluded>
		<bndbox>
			<xmin>59</xmin>
			<xmax>86</xmax>
			<ymin>182</ymin>
			<ymax>231</ymax>
		</bndbox>
	</object>
	<object>
		<name>yellow</name>
		<pose>Unspecified</pose>
		<truncated>0</truncated>
		<difficult>0</difficult>
		<occluded>0</occluded>
		<bndbox>
			<xmin>107</xmin>
			<xmax>116</xmax>
			<ymin>171</ymin>
			<ymax>184</ymax>
		</bndbox>
	</object>
	<object>
		<name>yellow</name>
		<pose>Unspecified</pose>
		<truncated>0</truncated>
		<difficult>0</difficult>
		<occluded>0</occluded>
		<bndbox>
			<xmin>153</xmin>
			<xmax>162</xmax>
			<ymin>172</ymin>
			<ymax>184</ymax>
		</bndbox>
	</object>
	<object>
		<name>yellow</name>
		<pose>Unspecified</pose>
		<truncated>0</truncated>
		<difficult>0</difficult>
		<occluded>0</occluded>
		<bndbox>
			<xmin>168</xmin>
			<xmax>175</xmax>
			<ymin>180</ymin>
			<ymax>193</ymax>
		</bndbox>
	</object>
	<object>
		<name>yellow</name>
		<pose>Unspecified</pose>
		<truncated>0</truncated>
		<difficult>0</difficult>
		<occluded>0</occluded>
		<bndbox>
			<xmin>246</xmin>
			<xmax>272</xmax>
			<ymin>106</ymin>
			<ymax>143</ymax>
		</bndbox>
	</object>
</annotation>
